setup.py
wesell/__init__.py
wesell/djson.py
wesell/exceptions.py
wesell/filehash.py
wesell/func.py
wesell/rpc.py
wesell.egg-info/PKG-INFO
wesell.egg-info/SOURCES.txt
wesell.egg-info/dependency_links.txt
wesell.egg-info/not-zip-safe
wesell.egg-info/requires.txt
wesell.egg-info/top_level.txt
wesell/flask/__init__.py
wesell/flask/api_clients.py
wesell/flask/application.py
wesell/flask/cacheable.py
wesell/flask/globals.py
wesell/flask/mail.py
wesell/flask/rpc_interface.py
wesell/flask/sqllog.py
wesell/sqlalchemy/__init__.py
wesell/sqlalchemy/types.py